wlts/__init__.py
wlts/__init__.pyi
wlts/allen.py
wlts/allen.pyi
wlts/cli.py
wlts/cli.pyi
wlts/collection.py
wlts/collection.pyi
wlts/trajectories.py
wlts/trajectories.pyi
wlts/trajectory.py
wlts/trajectory.pyi
wlts/utils.py
wlts/utils.pyi
wlts/version.py
wlts/version.pyi
wlts/wlts.py
wlts/wlts.pyi
wlts/templates/collection.html
wlts/templates/trajectory-item.html
wlts/templates/trajectory.html
wlts/templates/wlts.html
wlts_py-1.4.0.dist-info/METADATA
wlts_py-1.4.0.dist-info/WHEEL
wlts_py-1.4.0.dist-info/entry_points.txt
wlts_py-1.4.0.dist-info/top_level.txt
wlts_py-1.4.0.dist-info/RECORD
