Metadata-Version: 2.4
Name: wlts.py
Version: 1.4.0
Summary: .
Author-email: Brazil Data Cube Team <bdc.team@inpe.br>
License: GNU General Public License v3.0
Keywords: lulc
Classifier: Intended Audience :: Information Technology
Classifier: Intended Audience :: Science/Research
Classifier: License :: OSI Approved :: GNU General Public License v3 (GPLv3)
Classifier: Programming Language :: Python :: 3.8
Classifier: Programming Language :: Python :: 3.9
Classifier: Programming Language :: Python :: 3.10
Classifier: Programming Language :: Python :: 3.11
Classifier: Programming Language :: Python :: 3.12
Classifier: Topic :: Software Development :: Libraries :: Python Modules
Requires-Python: >=3.8
Requires-Dist: Click>=7.0
Requires-Dist: Jinja2>=2.11.1
Requires-Dist: descartes>=1.1.0
Requires-Dist: shapely>=1.7.1
Requires-Dist: pandas>=1.1
Requires-Dist: geopandas>=0.8.2
Requires-Dist: plotly>=6.0.0
Requires-Dist: rich>=13.9.2
Requires-Dist: lccs>=1.0
Requires-Dist: httpx>=0.19.0
Requires-Dist: nbformat>=4.2.0
Provides-Extra: dev
Requires-Dist: pre-commit; extra == "dev"
Provides-Extra: docs
Requires-Dist: Sphinx>=7.0; extra == "docs"
Requires-Dist: sphinx_rtd_theme; extra == "docs"
Requires-Dist: sphinx-copybutton; extra == "docs"
Requires-Dist: sphinx-tabs; extra == "docs"
Provides-Extra: tests
Requires-Dist: coverage>=6.4; extra == "tests"
Requires-Dist: coveralls>=3.3; extra == "tests"
Requires-Dist: pytest>=7.4; extra == "tests"
Requires-Dist: pytest-cov>=4.1; extra == "tests"
Requires-Dist: pytest-pep8>=1.0; extra == "tests"
Requires-Dist: pydocstyle>=4.0; extra == "tests"
Requires-Dist: isort>4.3; extra == "tests"
Requires-Dist: check-manifest>=0.40; extra == "tests"
Requires-Dist: respx>=0.22.0; extra == "tests"
Provides-Extra: all
Requires-Dist: wlts[docs,tests]; extra == "all"
